conversor_horas_trabalho/__init__.py
conversor_horas_trabalho/cli.py
conversor_horas_trabalho/converte_horas.py
conversor_horas_trabalho/converte_horas_semanais.py
conversor_horas_trabalho/total_horas_mes.py
conversor_horas_trabalho-0.1.1.dist-info/entry_points.txt
conversor_horas_trabalho-0.1.1.dist-info/LICENSE
conversor_horas_trabalho-0.1.1.dist-info/METADATA
conversor_horas_trabalho-0.1.1.dist-info/WHEEL
conversor_horas_trabalho-0.1.1.dist-info/RECORD
