Metadata-Version: 2.1
Name: conversor-horas-trabalho
Version: 0.1.1
Summary: 
License: FreeFreeWare
Author: Gabriel Nadai
Author-email: denadai123@gmail.com
Requires-Python: >=3.10,<4.0
Classifier: Development Status :: 5 - Production/Stable
Classifier: Environment :: Console
Classifier: License :: Other/Proprietary License
Classifier: Natural Language :: Portuguese (Brazilian)
Classifier: Programming Language :: Python :: 3
Classifier: Programming Language :: Python :: 3.10
Classifier: Programming Language :: Python :: 3.11
Classifier: Programming Language :: Python :: 3.12
Classifier: Topic :: Education
Requires-Dist: rich (>=13.9.2,<14.0.0)
Requires-Dist: typer (>=0.12.5,<0.13.0)
Project-URL: Bug Tracker, https://github.com/ogabrielnadai/conversor-horas-trabalho/issues
Project-URL: Código, https://github.com/ogabrielnadai/conversor-horas-trabalho
Project-URL: Documentação, https://conversor-horas-trabalho.readthedocs.io/pt-br/latest/
